Workbook

Sheet Read_Me
A1: Simplified Financial Management Workbook — template
A2: Author: Anicet Safari, CPA · Rebuilt template, October 2026
A4: What this file is
A5: A rebuilt version of the workbook design I delivered to a small Kigali company under a pro bono Fractional CFO engagement (May 2023 to date).
A6: The client file itself is not published. This template reproduces its structure and logic; the company and every figure in it are fictional.
A8: How it works (one data entry point, everything else calculated)
A9: 1. Settings — company name, financial year, opening balances.
A10: 2. Chart_of_Accounts — account codes, types and where each one appears in the statements.
A11: 3. Cash_Book — every receipt and payment, coded to an account. This is the only transaction entry sheet.
A12: 4. Budget — annual budget by account, phased by month.
A13: 5. Budget_vs_Actual — year-to-date budget, actual and variance for the month chosen in Settings.
A14: 6. Income_Statement, Balance_Sheet, Cash_Flow — produced automatically from the cash book.
... A20: Example input row: Cash_Book row 5 (first receipt of the year). Change any blue amount and every report and check updates.

Sheet Settings
A1: Settings
A3: Company name | B3: Example Tech Ltd (fictional)
A4: Financial year | B4: 2025
A5: Reporting month (1-12) for Budget_vs_Actual | B5: 12
A6: Opening cash at bank, 1 January | B6: 1500000
A7: Opening equipment at cost, 1 January | B7: 0
A8: Opening owner's capital, 1 January | B8: 1500000
A9: Variance threshold for comment (±) | B9: 0.1
A11: All amounts in Rwandan francs (RWF). Figures are fictional, entered by the author for illustration.

Sheet Chart_of_Accounts
A1: Chart of accounts
A3: Code | B3: Account name | C3: Type | D3: Statement line | E3: Cash flow class
A4: 1500 | B4: Office and IT equipment | C4: Asset | D4: Equipment at cost | E4: Investing
A5: 3000 | B5: Owner's capital introduced | C5: Equity | D5: Owner's capital | E5: Financing
A6: 3100 | B6: Owner's drawings | C6: Equity | D6: Owner's drawings | E6: Financing
A7: 4000 | B7: Software development services | C7: Income | D7: Revenue | E7: Operating
A8: 4100 | B8: IT support and maintenance | C8: Income | D8: Revenue | E8: Operating
A9: 4200 | B9: Training fees | C9: Income | D9: Revenue | E9: Operating
A10: 5000 | B10: Contractor and staff costs | C10: Expense | D10: Staff and contractors | E10: Operating
A11: 5100 | B11: Office rent | C11: Expense | D11: Premises | E11: Operating
A12: 5200 | B12: Internet and communication | C12: Expense | D12: Operating costs | E12: Operating
A13: 5300 | B13: Electricity and water | C13: Expense | D13: Premises | E13: Operating
A14: 5400 | B14: Transport | C14: Expense | D14: Operating costs | E14: Operating
A15: 5500 | B15: Software subscriptions | C15: Expense | D15: Operating costs | E15: Operating
... A18: 5800 | B18: Taxes, licences and RRA fees | C18: Expense | D18: Taxes and licences | E18: Operating
A20: Codes: 1xxx assets · 3xxx equity · 4xxx income · 5xxx expenses. Cash at bank is the cash book itself, so it has no code.

Sheet Cash_Book
A1: Cash book — bank account
A2: Enter one line per receipt or payment. Columns A–F are inputs; G–K are calculated.
A4: Date | B4: Reference | C4: Description | D4: Account code | E4: Receipt | F4: Payment | G4: Account name | H4: Type | I4: Month | J4: Net (receipt − payment) | K4: Running balance
A5: 45663 | B5: RC-001 | C5: Website build - client A, 1st instalment | D5: 4000 | E5: 1800000 | F5: 0 | G5: =IFERROR(INDEX(Chart_of_Accounts!$B$4:$B$18,MATCH(D5,Chart_of_Accounts!$A$4:$A$18,0)),"INVALID CODE") -> Software development services | H5: =IFERROR(INDEX(Chart_of_Accounts!$C$4:$C$18,MATCH(D5,Chart_of_Accounts!$A$4:$A$18,0)),"") -> Income | I5: =MONTH(A5) -> 1 | J5: =E5-F5 -> 1800000 | K5: =Settings!$B$6+J5 -> 3300000
A6: 45664 | B6: RC-S01 | C6: Monthly IT support - client B (January) | D6: 4100 | E6: 450000 | F6: 0 | G6: =IFERROR(INDEX(Chart_of_Accounts!$B$4:$B$18,MATCH(D6,Chart_of_Accounts!$A$4:$A$18,0)),"INVALID CODE") -> IT support and maintenance | H6: =IFERROR(INDEX(Chart_of_Accounts!$C$4:$C$18,MATCH(D6,Chart_of_Accounts!$A$4:$A$18,0)),"") -> Income | I6: =MONTH(A6) -> 1 | J6: =E6-F6 -> 450000 | K6: =K5+J6 -> 3750000
A7: 45667 | B7: PV-001 | C7: Office rent January | D7: 5100 | E7: 0 | F7: 350000 | G7: =IFERROR(INDEX(Chart_of_Accounts!$B$4:$B$18,MATCH(D7,Chart_of_Accounts!$A$4:$A$18,0)),"INVALID CODE") -> Office rent | H7: =IFERROR(INDEX(Chart_of_Accounts!$C$4:$C$18,MATCH(D7,Chart_of_Accounts!$A$4:$A$18,0)),"") -> Expense | I7: =MONTH(A7) -> 1 | J7: =E7-F7 -> -350000 | K7: =K6+J7 -> 3400000
A8: 45672 | B8: PV-002 | C8: Laptop purchase | D8: 1500 | E8: 0 | F8: 950000 | G8: =IFERROR(INDEX(Chart_of_Accounts!$B$4:$B$18,MATCH(D8,Chart_of_Accounts!$A$4:$A$18,0)),"INVALID CODE") -> Office and IT equipment | H8: =IFERROR(INDEX(Chart_of_Accounts!$C$4:$C$18,MATCH(D8,Chart_of_Accounts!$A$4:$A$18,0)),"") -> Asset | I8: =MONTH(A8) -> 1 | J8: =E8-F8 -> -950000 | K8: =K7+J8 -> 2450000
A9: 45682 | B9: PV-I01 | C9: Internet subscription (January) | D9: 5200 | E9: 0 | F9: 60000 | G9: =IFERROR(INDEX(Chart_of_Accounts!$B$4:$B$18,MATCH(D9,Chart_of_Accounts!$A$4:$A$18,0)),"INVALID CODE") -> Internet and communication | H9: =IFERROR(INDEX(Chart_of_Accounts!$C$4:$C$18,MATCH(D9,Chart_of_Accounts!$A$4:$A$18,0)),"") -> Expense | I9: =MONTH(A9) -> 1 | J9: =E9-F9 -> -60000 | K9: =K8+J9 -> 2390000
A10: 45683 | B10: PV-E01 | C10: Electricity and water (January) | D10: 5300 | E10: 0 | F10: 85000 | G10: =IFERROR(INDEX(Chart_of_Accounts!$B$4:$B$18,MATCH(D10,Chart_of_Accounts!$A$4:$A$18,0)),"INVALID CODE") -> Electricity and water | H10: =IFERROR(INDEX(Chart_of_Accounts!$C$4:$C$18,MATCH(D10,Chart_of_Accounts!$A$4:$A$18,0)),"") -> Expense | I10: =MONTH(A10) -> 1 | J10: =E10-F10 -> -85000 | K10: =K9+J10 -> 2305000
A11: 45688 | B11: PV-004 | C11: Contractor fees January | D11: 5000 | E11: 0 | F11: 700000 | G11: =IFERROR(INDEX(Chart_of_Accounts!$B$4:$B$18,MATCH(D11,Chart_of_Accounts!$A$4:$A$18,0)),"INVALID CODE") -> Contractor and staff costs | H11: =IFERROR(INDEX(Chart_of_Accounts!$C$4:$C$18,MATCH(D11,Chart_of_Accounts!$A$4:$A$18,0)),"") -> Expense | I11: =MONTH(A11) -> 1 | J11: =E11-F11 -> -700000 | K11: =K10+J11 -> 1605000
A12: 45695 | B12: RC-S02 | C12: Monthly IT support - client B (February) | D12: 4100 | E12: 450000 | F12: 0 | G12: =IFERROR(INDEX(Chart_of_Accounts!$B$4:$B$18,MATCH(D12,Chart_of_Accounts!$A$4:$A$18,0)),"INVALID CODE") -> IT support and maintenance | H12: =IFERROR(INDEX(Chart_of_Accounts!$C$4:$C$18,MATCH(D12,Chart_of_Accounts!$A$4:$A$18,0)),"") -> Income | I12: =MONTH(A12) -> 2 | J12: =E12-F12 -> 450000 | K12: =K11+J12 -> 2055000
A13: 45698 | B13: PV-005 | C13: Office rent February | D13: 5100 | E13: 0 | F13: 350000 | G13: =IFERROR(INDEX(Chart_of_Accounts!$B$4:$B$18,MATCH(D13,Chart_of_Accounts!$A$4:$A$18,0)),"INVALID CODE") -> Office rent | H13: =IFERROR(INDEX(Chart_of_Accounts!$C$4:$C$18,MATCH(D13,Chart_of_Accounts!$A$4:$A$18,0)),"") -> Expense | I13: =MONTH(A13) -> 2 | J13: =E13-F13 -> -350000 | K13: =K12+J13 -> 1705000
A14: 45708 | B14: PV-006 | C14: Cloud and software subscriptions | D14: 5500 | E14: 0 | F14: 120000 | G14: =IFERROR(INDEX(Chart_of_Accounts!$B$4:$B$18,MATCH(D14,Chart_of_Accounts!$A$4:$A$18,0)),"INVALID CODE") -> Software subscriptions | H14: =IFERROR(INDEX(Chart_of_Accounts!$C$4:$C$18,MATCH(D14,Chart_of_Accounts!$A$4:$A$18,0)),"") -> Expense | I14: =MONTH(A14) -> 2 | J14: =E14-F14 -> -120000 | K14: =K13+J14 -> 1585000
A15: 45713 | B15: PV-I02 | C15: Internet subscription (February) | D15: 5200 | E15: 0 | F15: 60000 | G15: =IFERROR(INDEX(Chart_of_Accounts!$B$4:$B$18,MATCH(D15,Chart_of_Accounts!$A$4:$A$18,0)),"INVALID CODE") -> Internet and communication | H15: =IFERROR(INDEX(Chart_of_Accounts!$C$4:$C$18,MATCH(D15,Chart_of_Accounts!$A$4:$A$18,0)),"") -> Expense | I15: =MONTH(A15) -> 2 | J15: =E15-F15 -> -60000 | K15: =K14+J15 -> 1525000
A16: 45714 | B16: PV-E02 | C16: Electricity and water (February) | D16: 5300 | E16: 0 | F16: 90000 | G16: =IFERROR(INDEX(Chart_of_Accounts!$B$4:$B$18,MATCH(D16,Chart_of_Accounts!$A$4:$A$18,0)),"INVALID CODE") -> Electricity and water | H16: =IFERROR(INDEX(Chart_of_Accounts!$C$4:$C$18,MATCH(D16,Chart_of_Accounts!$A$4:$A$18,0)),"") -> Expense | I16: =MONTH(A16) -> 2 | J16: =E16-F16 -> -90000 | K16: =K15+J16 -> 1435000
A17: 45716 | B17: PV-007 | C17: Contractor fees February | D17: 5000 | E17: 0 | F17: 700000 | G17: =IFERROR(INDEX(Chart_of_Accounts!$B$4:$B$18,MATCH(D17,Chart_of_Accounts!$A$4:$A$18,0)),"INVALID CODE") -> Contractor and staff costs | H17: =IFERROR(INDEX(Chart_of_Accounts!$C$4:$C$18,MATCH(D17,Chart_of_Accounts!$A$4:$A$18,0)),"") -> Expense | I17: =MONTH(A17) -> 2 | J17: =E17-F17 -> -700000 | K17: =K16+J17 -> 735000
... A82: 46022 | B82: PV-033 | C82: Contractor fees December | D82: 5000 | E82: 0 | F82: 800000 | G82: =IFERROR(INDEX(Chart_of_Accounts!$B$4:$B$18,MATCH(D82,Chart_of_Accounts!$A$4:$A$18,0)),"INVALID CODE") -> Contractor and staff costs | H82: =IFERROR(INDEX(Chart_of_Accounts!$C$4:$C$18,MATCH(D82,Chart_of_Accounts!$A$4:$A$18,0)),"") -> Expense | I82: =MONTH(A82) -> 12 | J82: =E82-F82 -> -800000 | K82: =K81+J82 -> 2687000
C83: Totals | E83: =SUM(E5:E82) -> 18850000 | F83: =SUM(F5:F82) -> 17663000
C84: Closing cash book balance | K84: =Settings!$B$6+E83-F83 -> 2687000

Sheet Budget
A1: Annual budget by account, phased monthly
A3: Code | B3: Account | C3: Jan | D3: Feb | E3: Mar | F3: Apr | G3: May | H3: Jun | I3: Jul | J3: Aug | K3: Sep | L3: Oct | M3: Nov | N3: Dec | O3: Annual
A4: 4000 | B4: =INDEX(Chart_of_Accounts!$B$4:$B$18,MATCH(A4,Chart_of_Accounts!$A$4:$A$18,0)) -> Software development services | C4: 1500000 | D4: 0 | E4: 1500000 | F4: 0 | G4: 0 | H4: 2000000 | I4: 0 | J4: 2000000 | K4: 0 | L4: 1500000 | M4: 0 | N4: 0 | O4: =SUM(C4:N4) -> 8500000
A5: 4100 | B5: =INDEX(Chart_of_Accounts!$B$4:$B$18,MATCH(A5,Chart_of_Accounts!$A$4:$A$18,0)) -> IT support and maintenance | C5: 450000 | D5: 450000 | E5: 450000 | F5: 450000 | G5: 450000 | H5: 450000 | I5: 450000 | J5: 450000 | K5: 450000 | L5: 450000 | M5: 450000 | N5: 450000 | O5: =SUM(C5:N5) -> 5400000
A6: 4200 | B6: =INDEX(Chart_of_Accounts!$B$4:$B$18,MATCH(A6,Chart_of_Accounts!$A$4:$A$18,0)) -> Training fees | C6: 0 | D6: 0 | E6: 0 | F6: 900000 | G6: 0 | H6: 0 | I6: 0 | J6: 0 | K6: 900000 | L6: 0 | M6: 0 | N6: 900000 | O6: =SUM(C6:N6) -> 2700000
A7: 5000 | B7: =INDEX(Chart_of_Accounts!$B$4:$B$18,MATCH(A7,Chart_of_Accounts!$A$4:$A$18,0)) -> Contractor and staff costs | C7: 700000 | D7: 700000 | E7: 700000 | F7: 700000 | G7: 700000 | H7: 700000 | I7: 850000 | J7: 850000 | K7: 850000 | L7: 850000 | M7: 850000 | N7: 850000 | O7: =SUM(C7:N7) -> 9300000
A8: 5100 | B8: =INDEX(Chart_of_Accounts!$B$4:$B$18,MATCH(A8,Chart_of_Accounts!$A$4:$A$18,0)) -> Office rent | C8: 350000 | D8: 350000 | E8: 350000 | F8: 350000 | G8: 350000 | H8: 350000 | I8: 350000 | J8: 350000 | K8: 350000 | L8: 350000 | M8: 350000 | N8: 350000 | O8: =SUM(C8:N8) -> 4200000
A9: 5200 | B9: =INDEX(Chart_of_Accounts!$B$4:$B$18,MATCH(A9,Chart_of_Accounts!$A$4:$A$18,0)) -> Internet and communication | C9: 60000 | D9: 60000 | E9: 60000 | F9: 60000 | G9: 60000 | H9: 60000 | I9: 60000 | J9: 60000 | K9: 60000 | L9: 60000 | M9: 60000 | N9: 60000 | O9: =SUM(C9:N9) -> 720000
A10: 5300 | B10: =INDEX(Chart_of_Accounts!$B$4:$B$18,MATCH(A10,Chart_of_Accounts!$A$4:$A$18,0)) -> Electricity and water | C10: 80000 | D10: 80000 | E10: 80000 | F10: 80000 | G10: 80000 | H10: 80000 | I10: 80000 | J10: 80000 | K10: 80000 | L10: 80000 | M10: 80000 | N10: 80000 | O10: =SUM(C10:N10) -> 960000
A11: 5400 | B11: =INDEX(Chart_of_Accounts!$B$4:$B$18,MATCH(A11,Chart_of_Accounts!$A$4:$A$18,0)) -> Transport | C11: 30000 | D11: 30000 | E11: 30000 | F11: 30000 | G11: 30000 | H11: 30000 | I11: 30000 | J11: 30000 | K11: 30000 | L11: 30000 | M11: 30000 | N11: 30000 | O11: =SUM(C11:N11) -> 360000
A12: 5500 | B12: =INDEX(Chart_of_Accounts!$B$4:$B$18,MATCH(A12,Chart_of_Accounts!$A$4:$A$18,0)) -> Software subscriptions | C12: 0 | D12: 120000 | E12: 0 | F12: 0 | G12: 0 | H12: 0 | I12: 0 | J12: 0 | K12: 0 | L12: 0 | M12: 0 | N12: 0 | O12: =SUM(C12:N12) -> 120000
A13: 5600 | B13: =INDEX(Chart_of_Accounts!$B$4:$B$18,MATCH(A13,Chart_of_Accounts!$A$4:$A$18,0)) -> Bank charges | C13: 4000 | D13: 4000 | E13: 4000 | F13: 4000 | G13: 4000 | H13: 4000 | I13: 4000 | J13: 4000 | K13: 4000 | L13: 4000 | M13: 4000 | N13: 4000 | O13: =SUM(C13:N13) -> 48000
A14: 5700 | B14: =INDEX(Chart_of_Accounts!$B$4:$B$18,MATCH(A14,Chart_of_Accounts!$A$4:$A$18,0)) -> Marketing | C14: 0 | D14: 0 | E14: 0 | F14: 0 | G14: 150000 | H14: 0 | I14: 0 | J14: 0 | K14: 0 | L14: 150000 | M14: 0 | N14: 0 | O14: =SUM(C14:N14) -> 300000
A15: 5800 | B15: =INDEX(Chart_of_Accounts!$B$4:$B$18,MATCH(A15,Chart_of_Accounts!$A$4:$A$18,0)) -> Taxes, licences and RRA fees | C15: 0 | D15: 0 | E15: 200000 | F15: 0 | G15: 0 | H15: 0 | I15: 0 | J15: 0 | K15: 0 | L15: 0 | M15: 0 | N15: 0 | O15: =SUM(C15:N15) -> 200000
A17: Budget figures are fictional assumptions entered by the author.

Sheet Budget_vs_Actual
A1: Budget vs actual — year to date
A2: ="Months 1 to "&Settings!$B$5&" of "&Settings!$B$4 -> Months 1 to 12 of 2025
A4: Code | B4: Account | C4: Type | D4: Budget YTD | E4: Actual YTD | F4: Variance | G4: Variance % | H4: Comment needed?
A5: =Budget!A4 -> 4000 | B5: =Budget!B4 -> Software development services | C5: =INDEX(Chart_of_Accounts!$C$4:$C$18,MATCH(A5,Chart_of_Accounts!$A$4:$A$18,0)) -> Income | D5: =SUMPRODUCT((COLUMN(Budget!$C4:$N4)-COLUMN(Budget!$C4)+1<=Settings!$B$5)*Budget!$C4:$N4) -> 8500000 | E5: =SUMIFS(Cash_Book!$E$5:$E$82,Cash_Book!$D$5:$D$82,A5,Cash_Book!$I$5:$I$82,"<="&Settings!$B$5)+SUMIFS(Cash_Book!$F$5:$F$82,Cash_Book!$D$5:$D$82,A5,Cash_Book!$I$5:$I$82,"<="&Settings!$B$5) -> 9300000 | F5: =IF(C5="Income",E5-D5,D5-E5) -> 800000 | G5: =IF(D5=0,0,F5/D5) -> 0.094117647 | H5: =IF(ABS(G5)>Settings!$B$9,"Yes","No") -> No
A6: =Budget!A5 -> 4100 | B6: =Budget!B5 -> IT support and maintenance | C6: =INDEX(Chart_of_Accounts!$C$4:$C$18,MATCH(A6,Chart_of_Accounts!$A$4:$A$18,0)) -> Income | D6: =SUMPRODUCT((COLUMN(Budget!$C5:$N5)-COLUMN(Budget!$C5)+1<=Settings!$B$5)*Budget!$C5:$N5) -> 5400000 | E6: =SUMIFS(Cash_Book!$E$5:$E$82,Cash_Book!$D$5:$D$82,A6,Cash_Book!$I$5:$I$82,"<="&Settings!$B$5)+SUMIFS(Cash_Book!$F$5:$F$82,Cash_Book!$D$5:$D$82,A6,Cash_Book!$I$5:$I$82,"<="&Settings!$B$5) -> 6000000 | F6: =IF(C6="Income",E6-D6,D6-E6) -> 600000 | G6: =IF(D6=0,0,F6/D6) -> 0.11111111 | H6: =IF(ABS(G6)>Settings!$B$9,"Yes","No") -> Yes
A7: =Budget!A6 -> 4200 | B7: =Budget!B6 -> Training fees | C7: =INDEX(Chart_of_Accounts!$C$4:$C$18,MATCH(A7,Chart_of_Accounts!$A$4:$A$18,0)) -> Income | D7: =SUMPRODUCT((COLUMN(Budget!$C6:$N6)-COLUMN(Budget!$C6)+1<=Settings!$B$5)*Budget!$C6:$N6) -> 2700000 | E7: =SUMIFS(Cash_Book!$E$5:$E$82,Cash_Book!$D$5:$D$82,A7,Cash_Book!$I$5:$I$82,"<="&Settings!$B$5)+SUMIFS(Cash_Book!$F$5:$F$82,Cash_Book!$D$5:$D$82,A7,Cash_Book!$I$5:$I$82,"<="&Settings!$B$5) -> 3050000 | F7: =IF(C7="Income",E7-D7,D7-E7) -> 350000 | G7: =IF(D7=0,0,F7/D7) -> 0.12962963 | H7: =IF(ABS(G7)>Settings!$B$9,"Yes","No") -> Yes
A8: =Budget!A7 -> 5000 | B8: =Budget!B7 -> Contractor and staff costs | C8: =INDEX(Chart_of_Accounts!$C$4:$C$18,MATCH(A8,Chart_of_Accounts!$A$4:$A$18,0)) -> Expense | D8: =SUMPRODUCT((COLUMN(Budget!$C7:$N7)-COLUMN(Budget!$C7)+1<=Settings!$B$5)*Budget!$C7:$N7) -> 9300000 | E8: =SUMIFS(Cash_Book!$E$5:$E$82,Cash_Book!$D$5:$D$82,A8,Cash_Book!$I$5:$I$82,"<="&Settings!$B$5)+SUMIFS(Cash_Book!$F$5:$F$82,Cash_Book!$D$5:$D$82,A8,Cash_Book!$I$5:$I$82,"<="&Settings!$B$5) -> 9500000 | F8: =IF(C8="Income",E8-D8,D8-E8) -> -200000 | G8: =IF(D8=0,0,F8/D8) -> -0.021505376 | H8: =IF(ABS(G8)>Settings!$B$9,"Yes","No") -> No
A9: =Budget!A8 -> 5100 | B9: =Budget!B8 -> Office rent | C9: =INDEX(Chart_of_Accounts!$C$4:$C$18,MATCH(A9,Chart_of_Accounts!$A$4:$A$18,0)) -> Expense | D9: =SUMPRODUCT((COLUMN(Budget!$C8:$N8)-COLUMN(Budget!$C8)+1<=Settings!$B$5)*Budget!$C8:$N8) -> 4200000 | E9: =SUMIFS(Cash_Book!$E$5:$E$82,Cash_Book!$D$5:$D$82,A9,Cash_Book!$I$5:$I$82,"<="&Settings!$B$5)+SUMIFS(Cash_Book!$F$5:$F$82,Cash_Book!$D$5:$D$82,A9,Cash_Book!$I$5:$I$82,"<="&Settings!$B$5) -> 4200000 | F9: =IF(C9="Income",E9-D9,D9-E9) -> 0 | G9: =IF(D9=0,0,F9/D9) -> 0 | H9: =IF(ABS(G9)>Settings!$B$9,"Yes","No") -> No
A10: =Budget!A9 -> 5200 | B10: =Budget!B9 -> Internet and communication | C10: =INDEX(Chart_of_Accounts!$C$4:$C$18,MATCH(A10,Chart_of_Accounts!$A$4:$A$18,0)) -> Expense | D10: =SUMPRODUCT((COLUMN(Budget!$C9:$N9)-COLUMN(Budget!$C9)+1<=Settings!$B$5)*Budget!$C9:$N9) -> 720000 | E10: =SUMIFS(Cash_Book!$E$5:$E$82,Cash_Book!$D$5:$D$82,A10,Cash_Book!$I$5:$I$82,"<="&Settings!$B$5)+SUMIFS(Cash_Book!$F$5:$F$82,Cash_Book!$D$5:$D$82,A10,Cash_Book!$I$5:$I$82,"<="&Settings!$B$5) -> 720000 | F10: =IF(C10="Income",E10-D10,D10-E10) -> 0 | G10: =IF(D10=0,0,F10/D10) -> 0 | H10: =IF(ABS(G10)>Settings!$B$9,"Yes","No") -> No
A11: =Budget!A10 -> 5300 | B11: =Budget!B10 -> Electricity and water | C11: =INDEX(Chart_of_Accounts!$C$4:$C$18,MATCH(A11,Chart_of_Accounts!$A$4:$A$18,0)) -> Expense | D11: =SUMPRODUCT((COLUMN(Budget!$C10:$N10)-COLUMN(Budget!$C10)+1<=Settings!$B$5)*Budget!$C10:$N10) -> 960000 | E11: =SUMIFS(Cash_Book!$E$5:$E$82,Cash_Book!$D$5:$D$82,A11,Cash_Book!$I$5:$I$82,"<="&Settings!$B$5)+SUMIFS(Cash_Book!$F$5:$F$82,Cash_Book!$D$5:$D$82,A11,Cash_Book!$I$5:$I$82,"<="&Settings!$B$5) -> 1020000 | F11: =IF(C11="Income",E11-D11,D11-E11) -> -60000 | G11: =IF(D11=0,0,F11/D11) -> -0.0625 | H11: =IF(ABS(G11)>Settings!$B$9,"Yes","No") -> No
A12: =Budget!A11 -> 5400 | B12: =Budget!B11 -> Transport | C12: =INDEX(Chart_of_Accounts!$C$4:$C$18,MATCH(A12,Chart_of_Accounts!$A$4:$A$18,0)) -> Expense | D12: =SUMPRODUCT((COLUMN(Budget!$C11:$N11)-COLUMN(Budget!$C11)+1<=Settings!$B$5)*Budget!$C11:$N11) -> 360000 | E12: =SUMIFS(Cash_Book!$E$5:$E$82,Cash_Book!$D$5:$D$82,A12,Cash_Book!$I$5:$I$82,"<="&Settings!$B$5)+SUMIFS(Cash_Book!$F$5:$F$82,Cash_Book!$D$5:$D$82,A12,Cash_Book!$I$5:$I$82,"<="&Settings!$B$5) -> 95000 | F12: =IF(C12="Income",E12-D12,D12-E12) -> 265000 | G12: =IF(D12=0,0,F12/D12) -> 0.73611111 | H12: =IF(ABS(G12)>Settings!$B$9,"Yes","No") -> Yes
A13: =Budget!A12 -> 5500 | B13: =Budget!B12 -> Software subscriptions | C13: =INDEX(Chart_of_Accounts!$C$4:$C$18,MATCH(A13,Chart_of_Accounts!$A$4:$A$18,0)) -> Expense | D13: =SUMPRODUCT((COLUMN(Budget!$C12:$N12)-COLUMN(Budget!$C12)+1<=Settings!$B$5)*Budget!$C12:$N12) -> 120000 | E13: =SUMIFS(Cash_Book!$E$5:$E$82,Cash_Book!$D$5:$D$82,A13,Cash_Book!$I$5:$I$82,"<="&Settings!$B$5)+SUMIFS(Cash_Book!$F$5:$F$82,Cash_Book!$D$5:$D$82,A13,Cash_Book!$I$5:$I$82,"<="&Settings!$B$5) -> 120000 | F13: =IF(C13="Income",E13-D13,D13-E13) -> 0 | G13: =IF(D13=0,0,F13/D13) -> 0 | H13: =IF(ABS(G13)>Settings!$B$9,"Yes","No") -> No
A14: =Budget!A13 -> 5600 | B14: =Budget!B13 -> Bank charges | C14: =INDEX(Chart_of_Accounts!$C$4:$C$18,MATCH(A14,Chart_of_Accounts!$A$4:$A$18,0)) -> Expense | D14: =SUMPRODUCT((COLUMN(Budget!$C13:$N13)-COLUMN(Budget!$C13)+1<=Settings!$B$5)*Budget!$C13:$N13) -> 48000 | E14: =SUMIFS(Cash_Book!$E$5:$E$82,Cash_Book!$D$5:$D$82,A14,Cash_Book!$I$5:$I$82,"<="&Settings!$B$5)+SUMIFS(Cash_Book!$F$5:$F$82,Cash_Book!$D$5:$D$82,A14,Cash_Book!$I$5:$I$82,"<="&Settings!$B$5) -> 48000 | F14: =IF(C14="Income",E14-D14,D14-E14) -> 0 | G14: =IF(D14=0,0,F14/D14) -> 0 | H14: =IF(ABS(G14)>Settings!$B$9,"Yes","No") -> No
A15: =Budget!A14 -> 5700 | B15: =Budget!B14 -> Marketing | C15: =INDEX(Chart_of_Accounts!$C$4:$C$18,MATCH(A15,Chart_of_Accounts!$A$4:$A$18,0)) -> Expense | D15: =SUMPRODUCT((COLUMN(Budget!$C14:$N14)-COLUMN(Budget!$C14)+1<=Settings!$B$5)*Budget!$C14:$N14) -> 300000 | E15: =SUMIFS(Cash_Book!$E$5:$E$82,Cash_Book!$D$5:$D$82,A15,Cash_Book!$I$5:$I$82,"<="&Settings!$B$5)+SUMIFS(Cash_Book!$F$5:$F$82,Cash_Book!$D$5:$D$82,A15,Cash_Book!$I$5:$I$82,"<="&Settings!$B$5) -> 150000 | F15: =IF(C15="Income",E15-D15,D15-E15) -> 150000 | G15: =IF(D15=0,0,F15/D15) -> 0.5 | H15: =IF(ABS(G15)>Settings!$B$9,"Yes","No") -> Yes
A16: =Budget!A15 -> 5800 | B16: =Budget!B15 -> Taxes, licences and RRA fees | C16: =INDEX(Chart_of_Accounts!$C$4:$C$18,MATCH(A16,Chart_of_Accounts!$A$4:$A$18,0)) -> Expense | D16: =SUMPRODUCT((COLUMN(Budget!$C15:$N15)-COLUMN(Budget!$C15)+1<=Settings!$B$5)*Budget!$C15:$N15) -> 200000 | E16: =SUMIFS(Cash_Book!$E$5:$E$82,Cash_Book!$D$5:$D$82,A16,Cash_Book!$I$5:$I$82,"<="&Settings!$B$5)+SUMIFS(Cash_Book!$F$5:$F$82,Cash_Book!$D$5:$D$82,A16,Cash_Book!$I$5:$I$82,"<="&Settings!$B$5) -> 180000 | F16: =IF(C16="Income",E16-D16,D16-E16) -> 20000 | G16: =IF(D16=0,0,F16/D16) -> 0.1 | H16: =IF(ABS(G16)>Settings!$B$9,"Yes","No") -> No
B18: Total income | D18: =SUMIFS(D5:D16,$C$5:$C$16,"Income") -> 16600000 | E18: =SUMIFS(E5:E16,$C$5:$C$16,"Income") -> 18350000
B19: Total expenses | D19: =SUMIFS(D5:D16,$C$5:$C$16,"Expense") -> 16208000 | E19: =SUMIFS(E5:E16,$C$5:$C$16,"Expense") -> 16033000
B20: Net surplus / (deficit) | D20: =D18-D19 -> 392000 | E20: =E18-E19 -> 2317000
A22: Favourable variances are positive: income above budget, or expenses below budget.

Sheet Income_Statement
A1: =Settings!$B$3 -> Example Tech Ltd (fictional)
A2: ="Income statement for the year ended 31 December "&Settings!$B$4 -> Income statement for the year ended 31 December 2025
A3: RWF · prepared from the cash book (cash basis)
A5: Revenue
A6: Revenue from services | B6: =SUMPRODUCT((COUNTIFS(Chart_of_Accounts!$A$4:$A$18,Cash_Book!$D$5:$D$82,Chart_of_Accounts!$C$4:$C$18,"Income")>0)*Cash_Book!$E$5:$E$82) -> 18350000
A8: Expenses
A9: Staff and contractors | B9: =SUMPRODUCT((COUNTIFS(Chart_of_Accounts!$A$4:$A$18,Cash_Book!$D$5:$D$82,Chart_of_Accounts!$D$4:$D$18,A9,Chart_of_Accounts!$C$4:$C$18,"Expense")>0)*Cash_Book!$F$5:$F$82) -> 9500000
A10: Premises | B10: =SUMPRODUCT((COUNTIFS(Chart_of_Accounts!$A$4:$A$18,Cash_Book!$D$5:$D$82,Chart_of_Accounts!$D$4:$D$18,A10,Chart_of_Accounts!$C$4:$C$18,"Expense")>0)*Cash_Book!$F$5:$F$82) -> 5220000
A11: Operating costs | B11: =SUMPRODUCT((COUNTIFS(Chart_of_Accounts!$A$4:$A$18,Cash_Book!$D$5:$D$82,Chart_of_Accounts!$D$4:$D$18,A11,Chart_of_Accounts!$C$4:$C$18,"Expense")>0)*Cash_Book!$F$5:$F$82) -> 1085000
A12: Finance costs | B12: =SUMPRODUCT((COUNTIFS(Chart_of_Accounts!$A$4:$A$18,Cash_Book!$D$5:$D$82,Chart_of_Accounts!$D$4:$D$18,A12,Chart_of_Accounts!$C$4:$C$18,"Expense")>0)*Cash_Book!$F$5:$F$82) -> 48000
A13: Taxes and licences | B13: =SUMPRODUCT((COUNTIFS(Chart_of_Accounts!$A$4:$A$18,Cash_Book!$D$5:$D$82,Chart_of_Accounts!$D$4:$D$18,A13,Chart_of_Accounts!$C$4:$C$18,"Expense")>0)*Cash_Book!$F$5:$F$82) -> 180000
A14: Total expenses | B14: =SUM(B9:B13) -> 16033000
A16: Net surplus / (deficit) for the year | B16: =B6-B14 -> 2317000

Sheet Balance_Sheet
A1: =Settings!$B$3 -> Example Tech Ltd (fictional)
A2: ="Balance sheet at 31 December "&Settings!$B$4 -> Balance sheet at 31 December 2025
A3: RWF
A5: Assets
A6: Equipment at cost | B6: =Settings!$B$7+SUMIFS(Cash_Book!$F$5:$F$82,Cash_Book!$D$5:$D$82,1500)-SUMIFS(Cash_Book!$E$5:$E$82,Cash_Book!$D$5:$D$82,1500) -> 1230000
A7: Cash at bank | B7: =Cash_Book!$K$84 -> 2687000
A8: Total assets | B8: =B6+B7 -> 3917000
A10: Owner's equity
A11: Opening owner's capital | B11: =Settings!$B$8 -> 1500000
A12: Capital introduced in the year | B12: =SUMIFS(Cash_Book!$E$5:$E$82,Cash_Book!$D$5:$D$82,3000) -> 500000
A13: Surplus / (deficit) for the year | B13: =Income_Statement!B16 -> 2317000
A14: Less: owner's drawings | B14: =-SUMIFS(Cash_Book!$F$5:$F$82,Cash_Book!$D$5:$D$82,3100) -> -400000
A15: Total owner's equity | B15: =SUM(B11:B14) -> 3917000
A17: Difference (must be zero) | B17: =B8-B15 -> 0
A19: Simplified balance sheet: no receivables, payables or depreciation, as the business records transactions when cash moves.

Sheet Cash_Flow
A1: =Settings!$B$3 -> Example Tech Ltd (fictional)
A2: ="Cash flow summary for the year ended 31 December "&Settings!$B$4 -> Cash flow summary for the year ended 31 December 2025
A4: Net cash from operating activities | B4: =SUMPRODUCT((COUNTIFS(Chart_of_Accounts!$A$4:$A$18,Cash_Book!$D$5:$D$82,Chart_of_Accounts!$E$4:$E$18,"Operating")>0)*Cash_Book!$J$5:$J$82) -> 2317000
A5: Net cash used in investing activities | B5: =SUMPRODUCT((COUNTIFS(Chart_of_Accounts!$A$4:$A$18,Cash_Book!$D$5:$D$82,Chart_of_Accounts!$E$4:$E$18,"Investing")>0)*Cash_Book!$J$5:$J$82) -> -1230000
A6: Net cash from financing activities | B6: =SUMPRODUCT((COUNTIFS(Chart_of_Accounts!$A$4:$A$18,Cash_Book!$D$5:$D$82,Chart_of_Accounts!$E$4:$E$18,"Financing")>0)*Cash_Book!$J$5:$J$82) -> 100000
A7: Net change in cash | B7: =SUM(B4:B6) -> 1187000
A8: Cash at 1 January | B8: =Settings!$B$6 -> 1500000
A9: Cash at 31 December | B9: =B7+B8 -> 2687000

Sheet Bank_Reconciliation
A1: Bank reconciliation at 31 December
A3: Balance per cash book | B3: =Cash_Book!$K$84 -> 2687000
A5: Balance per bank statement | B5: 3487000
A6: Add: receipts recorded, not yet credited by bank | B6: 0
A7: Less: payments recorded, not yet cleared (PV-033) | B7: -800000
A8: Adjusted bank balance | B8: =SUM(B5:B7) -> 2687000
A10: Difference (must be zero) | B10: =B3-B8 -> 0
A11: Status | B11: =IF(ABS(B10)<0.5,"RECONCILED","INVESTIGATE") -> RECONCILED

Sheet Checks
A1: Checks
A3: # | B3: Check | C3: Result
A4: 1 | B4: Balance sheet balances (assets = equity) | C4: =IF(ABS(Balance_Sheet!B17)<0.5,"PASS","FAIL") -> PASS
A5: 2 | B5: Every cash book line has a valid account code | C5: =IF(COUNTIF(Cash_Book!$G$5:$G$82,"INVALID CODE")=0,"PASS","FAIL") -> PASS
A6: 3 | B6: Cash flow closing cash = cash book closing balance | C6: =IF(ABS(Cash_Flow!B9-Cash_Book!$K$84)<0.5,"PASS","FAIL") -> PASS
A7: 4 | B7: Budget vs actual net surplus (full year) = income statement surplus | C7: =IF(Settings!$B$5<>12,"N/A (month<12)",IF(ABS(Budget_vs_Actual!E20-Income_Statement!B16)<0.5,"PASS","FAIL")) -> PASS
A8: 5 | B8: Bank reconciliation agrees | C8: =IF(Bank_Reconciliation!B11="RECONCILED","PASS","FAIL") -> PASS
B10: Overall | C10: =IF(COUNTIF(C4:C8,"FAIL")=0,"ALL PASS","REVIEW") -> ALL PASS
