Workbook

Sheet Read_Me
A1: Ministry X (fictional) — Financial Statements, FY 2025/26 (cash basis)
A2: Author: Anicet Safari, CPA · Illustrative work sample, October 2026 · All figures fictional, RWF thousands
A4: Purpose
A5: Shows how report specifications (report_specifications.md) translate into working statements that tie back to the ledger.
A7: Sheets
A8: Ledger — closing balances by economic code with original budget, final budget and actual (the single data source).
A9: Receipts_Payments — Statement of Cash Receipts and Payments (IPSAS cash basis), built with SUMIFS on the ledger.
A10: Budget_vs_Actual — Statement of Comparison of Budget and Actual Amounts (IPSAS 24 style), by statement line.
A11: Checks — tie-out tests: statements agree to the ledger and to each other, and closing cash agrees to the reconciled bank balance.
A13: Colour legend
A14: Blue text = input (edit these) · Black text = formula · Green text = link to another sheet
A16: Example row of inputs: Ledger row 6 (code 2211010, Office supplies) — change any blue amount and every statement and check updates.

Sheet Ledger
A1: Ledger balances by economic code — FY 2025/26 (RWF thousands)
A3: Economic code | B3: Account name | C3: Type | D3: Statement line | E3: Original budget | F3: Final budget | G3: Actual
A4: 1500010 | B4: Transfers received from Treasury | C4: Receipt | D4: Transfers from Treasury | E4: 4200000 | F4: 4350000 | G4: 4180500
A5: 1420010 | B5: Administrative fees | C5: Receipt | D5: Fees and charges | E5: 120000 | F5: 120000 | G5: 131240
A6: 2110010 | B6: Basic salaries - permanent staff | C6: Payment | D6: Compensation of employees | E6: 1850000 | F6: 1850000 | G6: 1842310
A7: 2110020 | B7: Allowances | C7: Payment | D7: Compensation of employees | E7: 240000 | F7: 250000 | G7: 236900
A8: 2120010 | B8: Employer pension contribution | C8: Payment | D8: Compensation of employees | E8: 92500 | F8: 92500 | G8: 92115
A9: 2211010 | B9: Office supplies | C9: Payment | D9: Use of goods and services | E9: 45000 | F9: 40000 | G9: 38770
A10: 2211020 | B10: Communication and internet | C10: Payment | D10: Use of goods and services | E10: 30000 | F10: 30000 | G10: 27450
A11: 2221010 | B11: Domestic travel | C11: Payment | D11: Use of goods and services | E11: 60000 | F11: 55000 | G11: 51980
A12: 2231010 | B12: Electricity | C12: Payment | D12: Use of goods and services | E12: 38000 | F12: 42000 | G12: 41600
A13: 2631010 | B13: Current transfers to districts | C13: Payment | D13: Grants and transfers | E13: 1300000 | F13: 1400000 | G13: 1365000
A14: 3111010 | B14: Buildings - construction | C14: Payment | D14: Acquisition of non-financial assets | E14: 520000 | F14: 560000 | G14: 402300
A15: 3112010 | B15: Machinery and equipment | C15: Payment | D15: Acquisition of non-financial assets | E15: 145000 | F15: 150000 | G15: 138640
B16: Total receipts | E16: =SUMIFS(E4:E15,$C$4:$C$15,"Receipt") -> 4320000 | F16: =SUMIFS(F4:F15,$C$4:$C$15,"Receipt") -> 4470000 | G16: =SUMIFS(G4:G15,$C$4:$C$15,"Receipt") -> 4311740
B17: Total payments | E17: =SUMIFS(E4:E15,$C$4:$C$15,"Payment") -> 4320500 | F17: =SUMIFS(F4:F15,$C$4:$C$15,"Payment") -> 4469500 | G17: =SUMIFS(G4:G15,$C$4:$C$15,"Payment") -> 4237065
B19: Opening cash balance (1 July 2025) | G19: 85320
B20: Reconciled bank balance, 30 June 2026 (from bank reconciliation, folder 07) | G20: 159995
A22: All amounts fictional, entered by the author for illustration.

Sheet Receipts_Payments
A1: Ministry X (fictional)
A2: Statement of Cash Receipts and Payments for the year ended 30 June 2026
A3: RWF thousands · IPSAS cash basis
A5: Line | B5: Note | C5: FY 2025/26
A6: Receipts
A7: Transfers from Treasury | B7: 1 | C7: =SUMIFS(Ledger!$G$4:$G$15,Ledger!$D$4:$D$15,A7) -> 4180500
A8: Fees and charges | B8: 2 | C8: =SUMIFS(Ledger!$G$4:$G$15,Ledger!$D$4:$D$15,A8) -> 131240
A9: Total receipts | C9: =SUM(C7:C8) -> 4311740
A11: Payments
A12: Compensation of employees | B12: 3 | C12: =SUMIFS(Ledger!$G$4:$G$15,Ledger!$D$4:$D$15,A12) -> 2171325
A13: Use of goods and services | B13: 4 | C13: =SUMIFS(Ledger!$G$4:$G$15,Ledger!$D$4:$D$15,A13) -> 159800
A14: Grants and transfers | B14: 5 | C14: =SUMIFS(Ledger!$G$4:$G$15,Ledger!$D$4:$D$15,A14) -> 1365000
A15: Acquisition of non-financial assets | B15: 6 | C15: =SUMIFS(Ledger!$G$4:$G$15,Ledger!$D$4:$D$15,A15) -> 540940
A16: Total payments | C16: =SUM(C12:C15) -> 4237065
A18: Net increase / (decrease) in cash | C18: =C9-C16 -> 74675
A19: Cash at 1 July 2025 | B19: 7 | C19: =Ledger!$G$19 -> 85320
A20: Cash at 30 June 2026 | B20: 7 | C20: =C18+C19 -> 159995

Sheet Budget_vs_Actual
A1: Ministry X (fictional)
A2: Statement of Comparison of Budget and Actual Amounts, year ended 30 June 2026
A3: RWF thousands · budget and actual on the same cash basis and classification
A5: Statement line | B5: Original budget | C5: Final budget | D5: Actual | E5: Variance (final − actual) | F5: Execution rate | G5: Explanation needed?
A6: Receipts
A7: Transfers from Treasury | B7: =SUMIFS(Ledger!$E$4:$E$15,Ledger!$D$4:$D$15,$A7) -> 4200000 | C7: =SUMIFS(Ledger!$F$4:$F$15,Ledger!$D$4:$D$15,$A7) -> 4350000 | D7: =SUMIFS(Ledger!$G$4:$G$15,Ledger!$D$4:$D$15,$A7) -> 4180500 | E7: =C7-D7 -> 169500 | F7: =IF(C7=0,0,D7/C7) -> 0.96103448 | G7: =IF(ABS(1-F7)>$B$22,"Yes","No") -> No
A8: Fees and charges | B8: =SUMIFS(Ledger!$E$4:$E$15,Ledger!$D$4:$D$15,$A8) -> 120000 | C8: =SUMIFS(Ledger!$F$4:$F$15,Ledger!$D$4:$D$15,$A8) -> 120000 | D8: =SUMIFS(Ledger!$G$4:$G$15,Ledger!$D$4:$D$15,$A8) -> 131240 | E8: =C8-D8 -> -11240 | F8: =IF(C8=0,0,D8/C8) -> 1.0936667 | G8: =IF(ABS(1-F8)>$B$22,"Yes","No") -> No
A9: Total receipts | B9: =SUM(B7:B8) -> 4320000 | C9: =SUM(C7:C8) -> 4470000 | D9: =SUM(D7:D8) -> 4311740 | E9: =SUM(E7:E8) -> 158260 | F9: =IF(C9=0,0,D9/C9) -> 0.96459508
A11: Payments
A12: Compensation of employees | B12: =SUMIFS(Ledger!$E$4:$E$15,Ledger!$D$4:$D$15,$A12) -> 2182500 | C12: =SUMIFS(Ledger!$F$4:$F$15,Ledger!$D$4:$D$15,$A12) -> 2192500 | D12: =SUMIFS(Ledger!$G$4:$G$15,Ledger!$D$4:$D$15,$A12) -> 2171325 | E12: =C12-D12 -> 21175 | F12: =IF(C12=0,0,D12/C12) -> 0.99034208 | G12: =IF(ABS(1-F12)>$B$22,"Yes","No") -> No
A13: Use of goods and services | B13: =SUMIFS(Ledger!$E$4:$E$15,Ledger!$D$4:$D$15,$A13) -> 173000 | C13: =SUMIFS(Ledger!$F$4:$F$15,Ledger!$D$4:$D$15,$A13) -> 167000 | D13: =SUMIFS(Ledger!$G$4:$G$15,Ledger!$D$4:$D$15,$A13) -> 159800 | E13: =C13-D13 -> 7200 | F13: =IF(C13=0,0,D13/C13) -> 0.95688623 | G13: =IF(ABS(1-F13)>$B$22,"Yes","No") -> No
A14: Grants and transfers | B14: =SUMIFS(Ledger!$E$4:$E$15,Ledger!$D$4:$D$15,$A14) -> 1300000 | C14: =SUMIFS(Ledger!$F$4:$F$15,Ledger!$D$4:$D$15,$A14) -> 1400000 | D14: =SUMIFS(Ledger!$G$4:$G$15,Ledger!$D$4:$D$15,$A14) -> 1365000 | E14: =C14-D14 -> 35000 | F14: =IF(C14=0,0,D14/C14) -> 0.975 | G14: =IF(ABS(1-F14)>$B$22,"Yes","No") -> No
A15: Acquisition of non-financial assets | B15: =SUMIFS(Ledger!$E$4:$E$15,Ledger!$D$4:$D$15,$A15) -> 665000 | C15: =SUMIFS(Ledger!$F$4:$F$15,Ledger!$D$4:$D$15,$A15) -> 710000 | D15: =SUMIFS(Ledger!$G$4:$G$15,Ledger!$D$4:$D$15,$A15) -> 540940 | E15: =C15-D15 -> 169060 | F15: =IF(C15=0,0,D15/C15) -> 0.76188732 | G15: =IF(ABS(1-F15)>$B$22,"Yes","No") -> Yes
A16: Total payments | B16: =SUM(B12:B15) -> 4320500 | C16: =SUM(C12:C15) -> 4469500 | D16: =SUM(D12:D15) -> 4237065 | E16: =SUM(E12:E15) -> 232435 | F16: =IF(C16=0,0,D16/C16) -> 0.9479953
A18: Net cash flow | B18: =B9-B16 -> -500 | C18: =C9-C16 -> 500 | D18: =D9-D16 -> 74675
A22: Variance threshold for explanation (absolute deviation from 100% execution) | B22: 0.1
A23: Assumption set by the author: lines executed outside 90%–110% of final budget need a narrative explanation in the notes.

Sheet Checks
A1: Tie-out checks
A3: # | B3: Check | C3: Value A | D3: Value B | E3: Difference | F3: Result
A4: 1 | B4: Statement total receipts = ledger total receipts | C4: =Receipts_Payments!C9 -> 4311740 | D4: =Ledger!$G$16 -> 4311740 | E4: =C4-D4 -> 0 | F4: =IF(ABS(E4)<0.5,"PASS","FAIL") -> PASS
A5: 2 | B5: Statement total payments = ledger total payments | C5: =Receipts_Payments!C16 -> 4237065 | D5: =Ledger!$G$17 -> 4237065 | E5: =C5-D5 -> 0 | F5: =IF(ABS(E5)<0.5,"PASS","FAIL") -> PASS
A6: 3 | B6: Budget vs actual: actual receipts = statement receipts | C6: =Budget_vs_Actual!D9 -> 4311740 | D6: =Receipts_Payments!C9 -> 4311740 | E6: =C6-D6 -> 0 | F6: =IF(ABS(E6)<0.5,"PASS","FAIL") -> PASS
A7: 4 | B7: Budget vs actual: actual payments = statement payments | C7: =Budget_vs_Actual!D16 -> 4237065 | D7: =Receipts_Payments!C16 -> 4237065 | E7: =C7-D7 -> 0 | F7: =IF(ABS(E7)<0.5,"PASS","FAIL") -> PASS
A8: 5 | B8: Every ledger line is mapped to a statement line (count mapped = count of lines) | C8: =SUMPRODUCT(--(Ledger!$D$4:$D$15<>"")) -> 12 | D8: =ROWS(Ledger!$D$4:$D$15) -> 12 | E8: =C8-D8 -> 0 | F8: =IF(ABS(E8)<0.5,"PASS","FAIL") -> PASS
A9: 6 | B9: Closing cash per statement = reconciled bank balance | C9: =Receipts_Payments!C20 -> 159995 | D9: =Ledger!$G$20 -> 159995 | E9: =C9-D9 -> 0 | F9: =IF(ABS(E9)<0.5,"PASS","FAIL") -> PASS
B11: All checks | F11: =IF(COUNTIF(F4:F9,"PASS")=6,"ALL PASS","REVIEW") -> ALL PASS
